AUTHORS.rst
CHANGELOG.rst
LICENSE
MANIFEST.in
README.rst
setup.py
panya_tube.egg-info/PKG-INFO
panya_tube.egg-info/SOURCES.txt
panya_tube.egg-info/dependency_links.txt
panya_tube.egg-info/not-zip-safe
panya_tube.egg-info/requires.txt
panya_tube.egg-info/top_level.txt
tube/__init__.py
tube/admin.py
tube/models.py
tube/tests.py
tube/widgets.py